projex/__init__.py
projex/main.py
projex/actions/__init__.py
projex/actions/env.py
projex/actions/helper.py
projex/actions/new.py
projex/actions/run.py
projex/actions/variables.py
projex/utils/__init__.py
projex/utils/config.py
projex/utils/cutie.py
projex/utils/parser.py
pyprojex-0.2.0.dist-info/licenses/LICENSE
pyprojex-0.2.0.dist-info/METADATA
pyprojex-0.2.0.dist-info/WHEEL
pyprojex-0.2.0.dist-info/entry_points.txt
pyprojex-0.2.0.dist-info/top_level.txt
pyprojex-0.2.0.dist-info/RECORD
