Metadata-Version: 2.4
Name: pyprojex
Version: 0.2.0
Summary: Python Project Manager
Author-email: Chocolate Loves You <chocolatefr@gmail.com>
License: GNU
Project-URL: Homepage, https://github.com/frchocolate/projex
Project-URL: Bug Tracker, https://github.com/frchocolate/projex/issues
Requires-Python: >=3.7
License-File: LICENSE
Dynamic: license-file
